odoo/addons/l10n_br_sale_commission/README.rst
odoo/addons/l10n_br_sale_commission/__init__.py
odoo/addons/l10n_br_sale_commission/__manifest__.py
odoo/addons/l10n_br_sale_commission/demo/res_config_settings_demo.xml
odoo/addons/l10n_br_sale_commission/demo/sale_order_demo.xml
odoo/addons/l10n_br_sale_commission/i18n/l10n_br_sale_commission.pot
odoo/addons/l10n_br_sale_commission/i18n/pt_BR.po
odoo/addons/l10n_br_sale_commission/models/__init__.py
odoo/addons/l10n_br_sale_commission/models/account_move_line.py
odoo/addons/l10n_br_sale_commission/models/commission_settlement.py
odoo/addons/l10n_br_sale_commission/models/res_config_settings.py
odoo/addons/l10n_br_sale_commission/models/sale_order_line.py
odoo/addons/l10n_br_sale_commission/readme/CONFIGURE.md
odoo/addons/l10n_br_sale_commission/readme/CONTRIBUTORS.md
odoo/addons/l10n_br_sale_commission/readme/DESCRIPTION.md
odoo/addons/l10n_br_sale_commission/readme/HISTORY.md
odoo/addons/l10n_br_sale_commission/readme/INSTALL.md
odoo/addons/l10n_br_sale_commission/readme/USAGE.md
odoo/addons/l10n_br_sale_commission/static/description/icon.png
odoo/addons/l10n_br_sale_commission/static/description/index.html
odoo/addons/l10n_br_sale_commission/tests/__init__.py
odoo/addons/l10n_br_sale_commission/tests/test_l10n_br_sale_commission.py
odoo/addons/l10n_br_sale_commission/views/res_config_settings_views.xml
odoo/addons/l10n_br_sale_commission/wizards/__init__.py
odoo/addons/l10n_br_sale_commission/wizards/wizard_invoice.py
odoo/addons/l10n_br_sale_commission/wizards/wizard_invoice.xml
odoo_addon_l10n_br_sale_commission-16.0.2.0.0.dist-info/METADATA
odoo_addon_l10n_br_sale_commission-16.0.2.0.0.dist-info/WHEEL
odoo_addon_l10n_br_sale_commission-16.0.2.0.0.dist-info/top_level.txt
odoo_addon_l10n_br_sale_commission-16.0.2.0.0.dist-info/RECORD
